{"cameraMode":{"drawMode":0,"name":"Shaded","section":"Shading Mode"},"sceneLighting":false,"audioPlay":false,"sceneViewState":{"m_AlwaysRefresh":false,"showFog":true,"showSkybox":false,"showFlares":true,"showImageEffects":true,"showParticleSystems":true,"showVisualEffectGraphs":true,"m_FxEnabled":true},"in2DMode":false,"pivot":{"x":-2.9802322387695315e-8,"y":0.1397373229265213,"z":0.0},"rotation":{"x":-0.10321515053510666,"y":-0.8237959146499634,"z":0.15740595757961274,"w":-0.5351743102073669},"size":0.2407696694135666,"orthographic":false}